ERA/__init__.py
ERA/core.py
era_algorithm-0.1.0.dist-info/LICENSE
era_algorithm-0.1.0.dist-info/METADATA
era_algorithm-0.1.0.dist-info/WHEEL
era_algorithm-0.1.0.dist-info/top_level.txt
era_algorithm-0.1.0.dist-info/RECORD
