Metadata-Version: 2.1
Name: era-algorithm
Version: 0.1.0
Summary: Eigensystem Realization Algorithm (ERA) functions for system identification
Author: Theodore Li
Author-email: theodoreli927@gmail.com
License: MIT
Classifier: Programming Language :: Python :: 3
Classifier: License :: OSI Approved :: MIT License
Classifier: Operating System :: OS Independent
Requires-Python: >=3.9
License-File: LICENSE
Requires-Dist: numpy
Requires-Dist: scipy
